om2m_client/__init__.py
om2m_client/client.py
om2m_client/enums.py
om2m_client/exceptions.py
om2m_client/models.py
om2m_client/test.py
om2m_client-0.1.3.dist-info/licenses/LICENSE
om2m_client-0.1.3.dist-info/METADATA
om2m_client-0.1.3.dist-info/WHEEL
om2m_client-0.1.3.dist-info/top_level.txt
om2m_client-0.1.3.dist-info/RECORD
