Metadata-Version: 2.4
Name: om2m-client
Version: 0.1.3
Summary: A client for interacting with OM2M CSE, compatible with CPython and MicroPython.
Home-page: https://github.com/SCRCE/micropython-om2m-client
Author: Ahmad Hammad, Omar Hourani
Author-email: Ahmad.Hammad@ieee.com, Omar.Hourani@ieee.org
Classifier: Development Status :: 4 - Beta
Classifier: Intended Audience :: Developers
Classifier: Programming Language :: Python :: Implementation :: CPython
Classifier: Programming Language :: Python :: Implementation :: MicroPython
License-File: LICENSE
Requires-Dist: requests
Provides-Extra: dev
Requires-Dist: pytest; extra == "dev"
Requires-Dist: flake8; extra == "dev"
Dynamic: author
Dynamic: author-email
Dynamic: classifier
Dynamic: description
Dynamic: description-content-type
Dynamic: home-page
Dynamic: license-file
Dynamic: provides-extra
Dynamic: requires-dist
Dynamic: summary
